{
    "pyr": {
        "Zymomonas mobilis": [
            486.0
        ],
        "Saccharomyces cerevisiae": [
            1.78,
            3.16302571,
            12.1,
            10.3,
            9.21,
            12.14,
            10.32,
            9.21,
            12.06,
            12.42,
            2.2,
            10.32,
            9.21
        ]
    },
    "REST": {
        "Zymomonas mobilis": [
            320.0,
            53.0,
            4.0,
            0.4
        ]
    }
}